<?xml version="1.0" encoding="UTF-8"?>
<databaseChangeLog
        xmlns="http://www.liquibase.org/xml/ns/dbchangelog"
        xmlns:xsi="http://www.w3.org/2001/XMLSchema-instance"
        xsi:schemaLocation="http://www.liquibase.org/xml/ns/dbchangelog
		http://www.liquibase.org/xml/ns/dbchangelog/dbchangelog-latest.xsd">


    <include file="01-create-table-searches.sql" relativeToChangelogFile="true"/>

    <changeSet id="1.1.1" author="alex_evdokimov">
        <tagDatabase tag="v-1.1-create-table-searches"/>
    </changeSet>

    <include file="02-create-table-search-results.sql" relativeToChangelogFile="true"/>

    <changeSet id="1.1.2" author="alex_evdokimov">
        <tagDatabase tag="v-1.1-create-table-search-results"/>
    </changeSet>

    <include file="03-create-table-depart-flights.sql" relativeToChangelogFile="true"/>

    <changeSet id="1.1.3" author="alex_evdokimov">
        <tagDatabase tag="v-1.1-create-table-depart-flights"/>
    </changeSet>

    <include file="04-create-table-return-flights.sql" relativeToChangelogFile="true"/>

    <changeSet id="1.1.4" author="alex_evdokimov">
        <tagDatabase tag="v-1.1-create-table-return-flights"/>
    </changeSet>

</databaseChangeLog>